dw_feature_util-0.5.dist-info/METADATA
dw_feature_util-0.5.dist-info/RECORD
dw_feature_util-0.5.dist-info/WHEEL
dw_feature_util-0.5.dist-info/top_level.txt
feature_util/__init__.py
feature_util/feature_producer.py
feature_util/indices/__init__.py
feature_util/indices/dowj.py
feature_util/indices/indices_feature_producer.py
feature_util/indices/nasdaq.py
feature_util/indices/sp500.py
feature_util/macro/__init__.py
feature_util/macro/us_treasury.py
feature_util/ohlc/__init__.py
feature_util/ohlc/bb.py
feature_util/ohlc/cci.py
feature_util/ohlc/force_index.py
feature_util/ohlc/macd.py
feature_util/ohlc/moving_average.py
feature_util/ohlc/ohlc_feature_producer.py
feature_util/ohlc/pct_change.py
feature_util/ohlc/time_lags.py
feature_util/ohlc/typical_price.py
feature_util/ohlc/y_direction.py
feature_util/sentiment/__init__.py
feature_util/sentiment/infotrie.py
test/__init__.py
test/test_pipeline.py
test/test_util.py
test/util.py
