Metadata-Version: 2.1
Name: dw-feature-util
Version: 0.5
Summary: Stock feature producers
Home-page: UNKNOWN
Author: Daniel Wang
Author-email: danielwpz@gmail.com
License: MIT
Platform: UNKNOWN
Requires-Dist: dw-datasource
Requires-Dist: pandas
Requires-Dist: numpy
